{
  "last_updated": "05/23/26",
  "total_icebergs": 42,
  "icebergs": [
    {
      "iceberg": "a76c",
      "dms_longitude": "34 6'W",
      "dms_lattitude": "57 48'S",
      "longitude": -346.0,
      "lattitude": -5748.0,
      "recent_observation": "05/19/26"
    },
    {
      "iceberg": "a81",
      "dms_longitude": "54 27'W",
      "dms_lattitude": "63 50'S",
      "longitude": -5427.0,
      "lattitude": -6350.0,
      "recent_observation": "05/21/26"
    },
    {
      "iceberg": "a82",
      "dms_longitude": "90 42'W",
      "dms_lattitude": "68 50'S",
      "longitude": -9042.0,
      "lattitude": -6850.0,
      "recent_observation": "05/21/26"
    },
    {
      "iceberg": "a83",
      "dms_longitude": "53 45'W",
      "dms_lattitude": "65 8'S",
      "longitude": -5345.0,
      "lattitude": -658.0,
      "recent_observation": "05/21/26"
    },
    {
      "iceberg": "a84",
      "dms_longitude": "108 13'W",
      "dms_lattitude": "72 23'S",
      "longitude": -10813.0,
      "lattitude": -7223.0,
      "recent_observation": "05/21/26"
    },
    {
      "iceberg": "a85",
      "dms_longitude": "56 30'W",
      "dms_lattitude": "66 53'S",
      "longitude": -5630.0,
      "lattitude": -6653.0,
      "recent_observation": "05/21/26"
    },
    {
      "iceberg": "b09b",
      "dms_longitude": "143 14'E",
      "dms_lattitude": "66 5'S",
      "longitude": 14314.0,
      "lattitude": -665.0,
      "recent_observation": "05/21/26"
    },
    {
      "iceberg": "b09g",
      "dms_longitude": "41 32'E",
      "dms_lattitude": "68 13'S",
      "longitude": 4132.0,
      "lattitude": -6813.0,
      "recent_observation": "05/21/26"
    },
    {
      "iceberg": "b22a",
      "dms_longitude": "178 10'E",
      "dms_lattitude": "69 51'S",
      "longitude": 17810.0,
      "lattitude": -6951.0,
      "recent_observation": "05/21/26"
    },
    {
      "iceberg": "b22f",
      "dms_longitude": "177 56'E",
      "dms_lattitude": "67 25'S",
      "longitude": 17756.0,
      "lattitude": -6725.0,
      "recent_observation": "05/21/26"
    },
    {
      "iceberg": "b22g",
      "dms_longitude": "159 51'W",
      "dms_lattitude": "66 47'S",
      "longitude": -15951.0,
      "lattitude": -6647.0,
      "recent_observation": "05/07/26"
    },
    {
      "iceberg": "b22h",
      "dms_longitude": "167 28'E",
      "dms_lattitude": "70 11'S",
      "longitude": 16728.0,
      "lattitude": -7011.0,
      "recent_observation": "05/21/26"
    },
    {
      "iceberg": "b22i",
      "dms_longitude": "179 15'W",
      "dms_lattitude": "68 9'S",
      "longitude": -17915.0,
      "lattitude": -689.0,
      "recent_observation": "05/02/26"
    },
    {
      "iceberg": "b29",
      "dms_longitude": "110 42'W",
      "dms_lattitude": "73 39'S",
      "longitude": -11042.0,
      "lattitude": -7339.0,
      "recent_observation": "05/21/26"
    },
    {
      "iceberg": "b51",
      "dms_longitude": "130 52'W",
      "dms_lattitude": "74 12'S",
      "longitude": -13052.0,
      "lattitude": -7412.0,
      "recent_observation": "05/21/26"
    },
    {
      "iceberg": "c15",
      "dms_longitude": "143 8'E",
      "dms_lattitude": "65 52'S",
      "longitude": 1438.0,
      "lattitude": -6552.0,
      "recent_observation": "05/21/26"
    },
    {
      "iceberg": "c18b",
      "dms_longitude": "47 23'E",
      "dms_lattitude": "66 59'S",
      "longitude": 4723.0,
      "lattitude": -6659.0,
      "recent_observation": "05/21/26"
    },
    {
      "iceberg": "c18c",
      "dms_longitude": "39 2'E",
      "dms_lattitude": "68 29'S",
      "longitude": 392.0,
      "lattitude": -6829.0,
      "recent_observation": "05/21/26"
    },
    {
      "iceberg": "c21b",
      "dms_longitude": "95 53'E",
      "dms_lattitude": "64 58'S",
      "longitude": 9553.0,
      "lattitude": -6458.0,
      "recent_observation": "05/21/26"
    },
    {
      "iceberg": "c24",
      "dms_longitude": "96 1'E",
      "dms_lattitude": "64 50'S",
      "longitude": 961.0,
      "lattitude": -6450.0,
      "recent_observation": "05/21/26"
    },
    {
      "iceberg": "c30",
      "dms_longitude": "96 16'E",
      "dms_lattitude": "64 46'S",
      "longitude": 9616.0,
      "lattitude": -6446.0,
      "recent_observation": "05/21/26"
    },
    {
      "iceberg": "c31",
      "dms_longitude": "96 30'E",
      "dms_lattitude": "64 43'S",
      "longitude": 9630.0,
      "lattitude": -6443.0,
      "recent_observation": "05/21/26"
    },
    {
      "iceberg": "c33",
      "dms_longitude": "101 16'E",
      "dms_lattitude": "65 13'S",
      "longitude": 10116.0,
      "lattitude": -6513.0,
      "recent_observation": "05/21/26"
    },
    {
      "iceberg": "c35",
      "dms_longitude": "142 59'E",
      "dms_lattitude": "66 13'S",
      "longitude": 14259.0,
      "lattitude": -6613.0,
      "recent_observation": "05/21/26"
    },
    {
      "iceberg": "c36",
      "dms_longitude": "146 29'E",
      "dms_lattitude": "67 27'S",
      "longitude": 14629.0,
      "lattitude": -6727.0,
      "recent_observation": "05/21/26"
    },
    {
      "iceberg": "c39",
      "dms_longitude": "74 58'E",
      "dms_lattitude": "69 9'S",
      "longitude": 7458.0,
      "lattitude": -699.0,
      "recent_observation": "04/22/26"
    },
    {
      "iceberg": "d15a",
      "dms_longitude": "81 47'E",
      "dms_lattitude": "66 40'S",
      "longitude": 8147.0,
      "lattitude": -6640.0,
      "recent_observation": "05/21/26"
    },
    {
      "iceberg": "d15b",
      "dms_longitude": "81 28'E",
      "dms_lattitude": "67 1'S",
      "longitude": 8128.0,
      "lattitude": -671.0,
      "recent_observation": "05/21/26"
    },
    {
      "iceberg": "d15c",
      "dms_longitude": "79 25'E",
      "dms_lattitude": "67 13'S",
      "longitude": 7925.0,
      "lattitude": -6713.0,
      "recent_observation": "05/21/26"
    },
    {
      "iceberg": "d15d",
      "dms_longitude": "79 17'E",
      "dms_lattitude": "67 17'S",
      "longitude": 7917.0,
      "lattitude": -6717.0,
      "recent_observation": "05/21/26"
    },
    {
      "iceberg": "d23",
      "dms_longitude": "74 33'E",
      "dms_lattitude": "69 29'S",
      "longitude": 7433.0,
      "lattitude": -6929.0,
      "recent_observation": "05/21/26"
    },
    {
      "iceberg": "d30b",
      "dms_longitude": "45 43'W",
      "dms_lattitude": "60 35'S",
      "longitude": -4543.0,
      "lattitude": -6035.0,
      "recent_observation": "05/21/26"
    },
    {
      "iceberg": "d32",
      "dms_longitude": "47 18'W",
      "dms_lattitude": "64 41'S",
      "longitude": -4718.0,
      "lattitude": -6441.0,
      "recent_observation": "05/21/26"
    },
    {
      "iceberg": "d33a",
      "dms_longitude": "57 19'W",
      "dms_lattitude": "64 41'S",
      "longitude": -5719.0,
      "lattitude": -6441.0,
      "recent_observation": "05/21/26"
    },
    {
      "iceberg": "d33b",
      "dms_longitude": "54 11'W",
      "dms_lattitude": "65 1'S",
      "longitude": -5411.0,
      "lattitude": -651.0,
      "recent_observation": "05/21/26"
    },
    {
      "iceberg": "d33c",
      "dms_longitude": "56 25'W",
      "dms_lattitude": "64 46'S",
      "longitude": -5625.0,
      "lattitude": -6446.0,
      "recent_observation": "05/21/26"
    },
    {
      "iceberg": "d34",
      "dms_longitude": "81 55'E",
      "dms_lattitude": "67 6'S",
      "longitude": 8155.0,
      "lattitude": -676.0,
      "recent_observation": "05/21/26"
    },
    {
      "iceberg": "d35",
      "dms_longitude": "48 24'W",
      "dms_lattitude": "63 21'S",
      "longitude": -4824.0,
      "lattitude": -6321.0,
      "recent_observation": "05/21/26"
    },
    {
      "iceberg": "d36",
      "dms_longitude": "86 50'E",
      "dms_lattitude": "66 15'S",
      "longitude": 8650.0,
      "lattitude": -6615.0,
      "recent_observation": "05/21/26"
    },
    {
      "iceberg": "d37",
      "dms_longitude": "36 20'E",
      "dms_lattitude": "69 12'S",
      "longitude": 3620.0,
      "lattitude": -6912.0,
      "recent_observation": "05/21/26"
    },
    {
      "iceberg": "uk324",
      "dms_longitude": "148 52'E",
      "dms_lattitude": "66 58'S",
      "longitude": 14852.0,
      "lattitude": -6658.0,
      "recent_observation": "05/21/26"
    },
    {
      "iceberg": "uk328",
      "dms_longitude": "149 3'E",
      "dms_lattitude": "66 6'S",
      "longitude": 1493.0,
      "lattitude": -666.0,
      "recent_observation": "05/19/26"
    }
  ]
}